{
  "terms": [
    "FKUI Vue Labs",
    "Tidsinmatning",
    "XTimeTextField",
    "FTable",
    "FTable",
    "FTablePageObject"
  ],
  "results": [
    {
      "url": "index.html",
      "title": "FKUI Vue Labs",
      "terms": []
    },
    {
      "url": "components/xtimetextfield.html",
      "title": "Tidsinmatning",
      "terms": [
        "XTimeTextField"
      ]
    },
    {
      "url": "components/ftable.html",
      "title": "FTable",
      "terms": [
        "FTable"
      ]
    },
    {
      "url": "pageobjects/ftablepageobject.html",
      "title": "FTablePageObject",
      "terms": []
    }
  ],
  "mapping": {
    "0": 0,
    "1": 1,
    "2": 1,
    "3": 2,
    "4": 2,
    "5": 3
  }
}
